rdecssupplier/__init__.py
rdecssupplier/es_DatabaseOperations.py
rdecssupplier/es_Metadata.py
rdecssupplier/es_Utility.py
rdecssupplier/es_supplier_demo.py
rdecssupplier/mainModel.py
rdecssupplier-1.2.9.dist-info/METADATA
rdecssupplier-1.2.9.dist-info/WHEEL
rdecssupplier-1.2.9.dist-info/top_level.txt
rdecssupplier-1.2.9.dist-info/RECORD
